[
  {
    "Name": "Adriano Drago",
    "Flag": ":flag_br:",
    "SWGOH": "<https://swgoh.gg/p/726114648/>",
    "UTC": "02:00"
  },
  {
    "Name": "ak47",
    "Flag": ":pirate_flag:",
    "SWGOH": "<https://swgoh.gg/p/812358224/>",
    "UTC": "18:00"
  },
  {
    "Name": "Alexandros Original21",
    "Flag": ":flag_us:",
    "SWGOH": "<https://swgoh.gg/p/859975729/>",
    "UTC": "21:30"
  },
  {
    "Name": "Bruju",
    "Flag": ":flag_es:",
    "SWGOH": "<https://swgoh.gg/p/277745721/>",
    "UTC": "18:00"
  },
  {
    "Name": "Bugs (Багc)",
    "Flag": ":flag_ru:",
    "SWGOH": "<https://swgoh.gg/p/926873692/>",
    "UTC": "14:30"
  },
  {
    "Name": "Canadafett",
    "Flag": ":flag_ca:",
    "SWGOH": "<https://swgoh.gg/p/722646324/>",
    "UTC": "4:00"
  },
  {
    "Name": "DarthTomas",
    "Flag": ":flag_us:",
    "SWGOH": "<https://swgoh.gg/p/636659365/>",
    "UTC": "1:00"
  },
  {
    "Name": "Fopam fairchier",
    "Flag": ":flag_fr:",
    "SWGOH": "<https://swgoh.gg/p/341438386/>",
    "UTC": "20:00"
  },
  {
    "Name": "Gossadjinn",
    "Flag": ":flag_fr:",
    "SWGOH": "<https://swgoh.gg/p/496644917/>",
    "UTC": "18:00"
  },
  {
    "Name": "Gotan",
    "Flag": ":flag_fr:",
    "SWGOH": "<https://swgoh.gg/p/885968255/>",
    "UTC": "17:00"
  },
  {
    "Name": "HLG",
    "Flag": ":flag_fr:",
    "SWGOH": "<https://swgoh.gg/p/527759877/>",
    "UTC": "17:00"
  },
  {
    "Name": "Khrizboh",
    "Flag": ":flag_dk:",
    "SWGOH": "<https://swgoh.gg/p/124123765/>",
    "UTC": "15:00"
  },
  {
    "Name": "Mara JadeBele",
    "Flag": ":flag_us:",
    "SWGOH": "<https://swgoh.gg/p/899536956/>",
    "UTC": "23:00"
  },
  {
    "Name": "megadit",
    "Flag": ":flag_ru:",
    "SWGOH": "<https://swgoh.gg/p/361447346/>",
    "UTC": "16:00"
  },
  {
    "Name": "Mhann Uhde Adare",
    "Flag": ":flag_us:",
    "SWGOH": "<https://swgoh.gg/p/291215714/>",
    "UTC": "3:00"
  },
  {
    "Name": "Mol Aport",
    "Flag": ":flag_kz:",
    "SWGOH": "<https://swgoh.gg/p/757518986/>",
    "UTC": "12:00"
  },
  {
    "Name": "MotMot",
    "Flag": ":flag_fr:",
    "SWGOH": "<https://swgoh.gg/p/938436566/>",
    "UTC": "15:00"
  },
  {
    "Name": "Muad'Dib",
    "Flag": ":flag_de:",
    "SWGOH": "<https://swgoh.gg/p/749278485/>",
    "UTC": "22:00"
  },
  {
    "Name": "Poisson",
    "Flag": ":flag_fr:",
    "SWGOH": "<https://swgoh.gg/p/735553425/>",
    "UTC": "21:00"
  },
  {
    "Name": "Pukidukii",
    "Flag": ":pirate_flag:",
    "SWGOH": "<https://swgoh.gg/p/497195927/>",
    "UTC": "13:00"
  },
  {
    "Name": "razvangry",
    "Flag": ":flag_ro:",
    "SWGOH": "<https://swgoh.gg/p/233396547/>",
    "UTC": "17:00"
  },
  {
    "Name": "Romulas",
    "Flag": ":flag_ru:",
    "SWGOH": "<https://swgoh.gg/p/617723856/>",
    "UTC": "14:00"
  },
  {
    "Name": "Samsonnyte",
    "Flag": ":flag_au:",
    "SWGOH": "<https://swgoh.gg/p/645558847/>",
    "UTC": "8:00"
  },
  {
    "Name": "Syndulla",
    "Flag": ":flag_kr:",
    "SWGOH": "<https://swgoh.gg/p/754447966/>",
    "UTC": "10:00"
  },
  {
    "Name": "Thorskrieger",
    "Flag": ":flag_de:",
    "SWGOH": "<https://swgoh.gg/p/881346355/>",
    "UTC": "18:00"
  },
  {
    "Name": "Trufra Cadav",
    "Flag": ":flag_us:",
    "SWGOH": "<https://swgoh.gg/p/374553829/>",
    "UTC": "3:00"
  },
  {
    "Name": "Tunkson",
    "Flag": ":flag_us:",
    "SWGOH": "<https://swgoh.gg/p/875992967/>",
    "UTC": "0:00"
  },
  {
    "Name": "Wollowitz",
    "Flag": ":flag_nl:",
    "SWGOH": "<https://swgoh.gg/p/845621817/>",
    "UTC": "19:00"
  }
]
